einkaufszettel.py
einkaufszettel-0.1.2.dist-info/licenses/LICENSE
einkaufszettel-0.1.2.dist-info/METADATA
einkaufszettel-0.1.2.dist-info/WHEEL
einkaufszettel-0.1.2.dist-info/top_level.txt
einkaufszettel-0.1.2.dist-info/RECORD
