Metadata-Version: 2.4
Name: einkaufszettel
Version: 0.1.2
Summary: Pythonic Einkaufszettel API
Requires-Python: >=3.11
License-File: LICENSE
Dynamic: license-file
